AUTHORS
LICENSE
MANIFEST.in
README.md
setup.cfg
setup.py
ecm/__init__.py
ecm/menu.py
ecm/urls.py
ecm.egg-info/PKG-INFO
ecm.egg-info/SOURCES.txt
ecm.egg-info/dependency_links.txt
ecm.egg-info/entry_points.txt
ecm.egg-info/not-zip-safe
ecm.egg-info/requires.txt
ecm.egg-info/top_level.txt
ecm/admin/__init__.py
ecm/admin/cli.py
ecm/admin/util.py
ecm/admin/cmd/__init__.py
ecm/admin/cmd/create.py
ecm/admin/cmd/daemon.py
ecm/admin/cmd/dump.py
ecm/admin/cmd/fuzzwork_patch_mysql.sql
ecm/admin/cmd/init.py
ecm/admin/cmd/load.py
ecm/admin/cmd/manage.py
ecm/admin/cmd/run.py
ecm/admin/cmd/upgrade.py
ecm/admin/instance_template/__init__.py
ecm/admin/instance_template/manage.py
ecm/admin/instance_template/settings.ini
ecm/admin/instance_template/settings.py
ecm/admin/instance_template/examples/apache_mod_wsgi_vhost.example
ecm/admin/instance_template/examples/apache_reverse_proxy.example
ecm/admin/instance_template/examples/phpbb2_simple_auth.php
ecm/admin/instance_template/examples/phpbb2_sync.py
ecm/admin/instance_template/examples/phpbb3_simple_auth.php
ecm/admin/instance_template/examples/phpbb3_sync.php
ecm/admin/instance_template/wsgi/ecm.wsgi
ecm/apps/__init__.py
ecm/apps/alerts/__init__.py
ecm/apps/alerts/admin.py
ecm/apps/alerts/alerts.py
ecm/apps/alerts/models.py
ecm/apps/alerts/observe.py
ecm/apps/alerts/urls.py
ecm/apps/alerts/views.py
ecm/apps/alerts/locale/de_DE/LC_MESSAGES/django.po
ecm/apps/alerts/locale/en_US/LC_MESSAGES/django.po
ecm/apps/alerts/locale/fr_FR/LC_MESSAGES/django.po
ecm/apps/alerts/migrations/0001_initial.py
ecm/apps/alerts/migrations/0002_auto__del_field_observerspec_app.py
ecm/apps/alerts/migrations/__init__.py
ecm/apps/alerts/templates/ecm/alerts/list.html
ecm/apps/common/__init__.py
ecm/apps/common/admin.py
ecm/apps/common/api.py
ecm/apps/common/auth.py
ecm/apps/common/eft.py
ecm/apps/common/models.py
ecm/apps/common/fixtures/0006_apicall_data.json
ecm/apps/common/fixtures/0007_colorthreshold_data.json
ecm/apps/common/locale/de_DE/LC_MESSAGES/django.po
ecm/apps/common/locale/en_US/LC_MESSAGES/django.po
ecm/apps/common/locale/fr_FR/LC_MESSAGES/django.po
ecm/apps/common/migrations/0001_initial.py
