Metadata-Version: 1.1
Name: ecm
Version: 2.2.5
Summary: EVE Corp Management is a management and decision-making helper-application for EVE Online.
Home-page: https://github.com/evecm/ecm
Author: ggrog
Author-email: ecm@ggrog.com
License: GPLv3
Download-URL: https://pypi.python.org/pypi/ecm
Keywords: eve-online,django,corporation,management
Platform: any
Classifier: Development Status :: 5 - Production/Stable
Classifier: Environment :: Web Environment
Classifier: Framework :: Django
Classifier: License :: OSI Approved :: GNU General Public License (GPL)
Classifier: Operating System :: OS Independent
Classifier: Programming Language :: Python
Classifier: Programming Language :: Python :: 2.5
Classifier: Programming Language :: Python :: 2.6
Classifier: Programming Language :: Python :: 2.7
Classifier: Topic :: Games/Entertainment
Classifier: Topic :: Internet :: WWW/HTTP :: WSGI :: Application
Provides: ecm
